appdata/__init__.py
appdata/lock.py
appdata/utils.py
tests/__init__.py
tests/test_lock.py
tests/test_paths.py
tests/test_utils.py
appdata-2.2.0.dist-info/LICENSE.md
appdata-2.2.0.dist-info/METADATA
appdata-2.2.0.dist-info/WHEEL
appdata-2.2.0.dist-info/top_level.txt
appdata-2.2.0.dist-info/RECORD
