Metadata-Version: 2.1
Name: appdata
Version: 2.2.0
Summary: Utils to manage application data folder.
Home-page: https://github.com/VoIlAlex/appdata
Download-URL: https://github.com/VoIlAlex/appdata/archive/v1.2.0.tar.gz
Author: voilalex
Author-email: ilya.vouk@gmail.com
License: MIT
Keywords: utils,filesystem,paths,resources
Classifier: Development Status :: 5 - Production/Stable
Classifier: Environment :: Console :: Curses
Classifier: Topic :: Utilities
Classifier: Topic :: System :: Filesystems
Classifier: Programming Language :: Python :: 3.5
Classifier: Programming Language :: Python :: 3.6
Classifier: Programming Language :: Python :: 3.7
Classifier: Programming Language :: Python :: 3.8
License-File: LICENSE.md
